{
  "id": 86,
  "title": "Top 6 Core App Dashboard Building Tools",
  "title_cn": "6 个最佳核心应用仪表盘构建工具",
  "title_ja": "コアアプリダッシュボード構築ツールのトップ6",
  "description": "Easily create data-driven dashboards with these no-code/low-code tools.",
  "description_cn": "使用这些无代码（零代码）/低代码工具轻松创建数据驱动的仪表盘。",
  "description_ja": "これらのノーコード／ローコードツールを使用して、データ駆動型のダッシュボードを簡単に作成できます。",
  "slug": "core-app-dashboard-building-tools",
  "publishedAt": "2024-10-12T11:50:14.194Z",
  "status": "published",
  "tags": [
    {
      "createdAt": "2024-06-16T04:07:19.160Z",
      "updatedAt": "2024-11-24T05:34:17.312Z",
      "id": 1,
      "title": "No code",
      "title_cn": "无代码",
      "sort": 1,
      "description": "",
      "description_cn": "",
      "displayOnPage": false,
      "slug": "",
      "displayOnBlog": null,
      "keywords": "",
      "keywords_cn": "",
      "title_ja": "コードなし",
      "description_ja": "",
      "keywords_ja": "",
      "createdById": 1,
      "updatedById": 9,
      "articlesTags": {
        "createdAt": "2024-10-12T12:33:44.477Z",
        "updatedAt": "2024-10-12T12:33:44.477Z",
        "tagId": 1,
        "articleId": 86
      }
    },
    {
      "createdAt": "2024-07-06T09:44:33.094Z",
      "updatedAt": "2024-11-24T05:34:19.706Z",
      "id": 17,
      "title": "best no code tools",
      "title_cn": "最佳无代码工具",
      "sort": 17,
      "description": null,
      "description_cn": null,
      "displayOnPage": null,
      "slug": null,
      "displayOnBlog": null,
      "keywords": null,
      "keywords_cn": null,
      "title_ja": "最高のノーコードツール",
      "description_ja": "説明はまだありません。",
      "keywords_ja": "ノーコード, ツール, ベスト",
      "createdById": 1,
      "updatedById": 9,
      "articlesTags": {
        "createdAt": "2024-10-12T12:33:44.478Z",
        "updatedAt": "2024-10-12T12:33:44.478Z",
        "tagId": 17,
        "articleId": 86
      }
    },
    {
      "createdAt": "2024-07-09T12:38:10.829Z",
      "updatedAt": "2024-11-24T05:34:20.070Z",
      "id": 19,
      "title": "No-Code News",
      "title_cn": "无代码资讯",
      "sort": 19,
      "description": "Stay updated with the latest news in the No-Code universe.",
      "description_cn": "无代码领域的最新信息。",
      "displayOnPage": true,
      "slug": "nocode-news",
      "displayOnBlog": true,
      "keywords": "No-code news, No-code updates, No-code technology, No-code trends, Latest in no-code, No-code insights, No-code platforms",
      "keywords_cn": "无代码新闻, 无代码更新, 无代码技术, 无代码趋势, 最新无代码信息, 无代码洞察, 无代码平台",
      "title_ja": "ノーコードニュース",
      "description_ja": "ノーコードの世界の最新ニュースを常に把握しましょう。",
      "keywords_ja": "ノーコードニュース, ノーコード更新, ノーコード技術, ノーコードトレンド, 最新のノーコード情報, ノーコードの洞察, ノーコードプラットフォーム",
      "createdById": 1,
      "updatedById": 9,
      "articlesTags": {
        "createdAt": "2024-10-12T12:33:44.477Z",
        "updatedAt": "2024-10-12T12:33:44.477Z",
        "tagId": 19,
        "articleId": 86
      }
    },
    {
      "createdAt": "2024-08-29T17:09:45.850Z",
      "updatedAt": "2024-11-24T05:34:27.012Z",
      "id": 57,
      "title": "low-code crm",
      "title_cn": "低代码 crm",
      "sort": 57,
      "description": null,
      "description_cn": null,
      "displayOnPage": null,
      "slug": null,
      "displayOnBlog": null,
      "keywords": null,
      "keywords_cn": null,
      "title_ja": "ローコードCRM",
      "description_ja": "説明はまだありません。",
      "keywords_ja": "ローコード, CRM",
      "createdById": 1,
      "updatedById": 9,
      "articlesTags": {
        "createdAt": "2024-10-12T12:33:44.478Z",
        "updatedAt": "2024-10-12T12:33:44.478Z",
        "tagId": 57,
        "articleId": 86
      }
    },
    {
      "createdAt": "2024-08-29T17:10:24.642Z",
      "updatedAt": "2024-11-24T05:34:27.549Z",
      "id": 60,
      "title": "no code crm",
      "title_cn": "no code crm",
      "sort": 60,
      "description": null,
      "description_cn": null,
      "displayOnPage": null,
      "slug": null,
      "displayOnBlog": null,
      "keywords": null,
      "keywords_cn": null,
      "title_ja": "ノーコードCRM",
      "description_ja": "ノーコードCRMの説明をここに追加してください。",
      "keywords_ja": "ノーコード, CRM",
      "createdById": 1,
      "updatedById": 9,
      "articlesTags": {
        "createdAt": "2024-10-12T12:33:44.478Z",
        "updatedAt": "2024-10-12T12:33:44.478Z",
        "tagId": 60,
        "articleId": 86
      }
    },
    {
      "createdAt": "2024-10-12T12:15:17.015Z",
      "updatedAt": "2024-11-24T05:34:29.779Z",
      "id": 72,
      "title": "Core App Dashboard",
      "title_cn": "核心应用仪表盘",
      "sort": 72,
      "description": null,
      "description_cn": null,
      "displayOnPage": null,
      "slug": null,
      "displayOnBlog": null,
      "keywords": null,
      "keywords_cn": null,
      "title_ja": "コアアプリダッシュボード",
      "description_ja": "リリースノート",
      "keywords_ja": null,
      "createdById": 3,
      "updatedById": 9,
      "articlesTags": {
        "createdAt": "2024-10-12T12:33:44.478Z",
        "updatedAt": "2024-10-12T12:33:44.478Z",
        "tagId": 72,
        "articleId": 86
      }
    }
  ],
  "sub_tags": [],
  "category": null,
  "cover": {
    "createdAt": "2024-10-21T00:54:39.756Z",
    "updatedAt": "2024-10-21T00:54:39.756Z",
    "id": 442,
    "title": "Frame 12 (1)",
    "filename": "c6531d478d2b2ee40272f22f67057152.png",
    "extname": ".png",
    "size": 233498,
    "mimetype": "image/png",
    "meta": {},
    "path": "",
    "url": "https://static-docs.nocobase.com/c6531d478d2b2ee40272f22f67057152.png",
    "preview": "https://static-docs.nocobase.com/c6531d478d2b2ee40272f22f67057152.png",
    "storageId": 2,
    "createdById": 3,
    "updatedById": 3
  },
  "hideOnListPage": false,
  "hideOnBlog": true,
  "updatedAt": "2025-06-12T04:24:13.101Z",
  "author": "Zhang Lu",
  "ai_generated": false,
  "ai_generated_cn": null,
  "ai_generated_ja": true
}