{
  "id": 957,
  "title": "NocoBase v2.1.0-alpha.13: add js variables to event flow",
  "title_cn": "NocoBase v2.1.0-alpha.13：事件流添加 js 变量",
  "title_ja": "NocoBase v2.1.0-alpha.13：イベントフローに JS 変数を追加しました",
  "description": "Release Note of v2.1.0-alpha.13",
  "description_cn": "v2.1.0-alpha.13 更新日志",
  "description_ja": "v2.1.0-alpha.13 リリースノート",
  "slug": "v2.1.0-alpha.13",
  "publishedAt": "2026-03-27T00:00:00.000Z",
  "status": "published",
  "tags": [
    {
      "createdAt": "2024-06-18T06:25:03.110Z",
      "updatedAt": "2024-11-24T05:34:17.666Z",
      "id": 4,
      "title": "Release Notes",
      "title_cn": "发布日志",
      "sort": 4,
      "description": "Learn about the latest features, improvements, and bug fixes.",
      "description_cn": "了解最新功能、改进和错误修复。",
      "displayOnPage": true,
      "slug": "release-notes",
      "displayOnBlog": true,
      "keywords": "NocoBase release notes, software updates, version releases, NocoBase updates, latest features, release announcements, product updates",
      "keywords_cn": "NocoBase发布说明, 软件更新, 版本发布, NocoBase更新, 最新功能, 发布公告, 产品更新",
      "title_ja": "リリースノート",
      "description_ja": "最新の機能、改善点、およびバグ修正について学びましょう。",
      "keywords_ja": "NocoBaseリリースノート, ソフトウェアアップデート, バージョンリリース, NocoBaseアップデート, 最新機能, リリースアナウンス, 製品アップデート",
      "createdById": 1,
      "updatedById": 9,
      "articlesTags": {
        "createdAt": "2026-03-27T05:46:15.615Z",
        "updatedAt": "2026-03-27T05:46:15.615Z",
        "tagId": 4,
        "articleId": 957
      }
    }
  ],
  "sub_tags": [
    {
      "createdAt": "2025-01-22T06:50:37.402Z",
      "updatedAt": "2025-01-22T06:50:37.402Z",
      "id": 115,
      "title": "Alpha",
      "title_cn": null,
      "sort": 114,
      "description": null,
      "description_cn": null,
      "displayOnPage": null,
      "slug": null,
      "displayOnBlog": null,
      "keywords": null,
      "keywords_cn": null,
      "title_ja": null,
      "description_ja": null,
      "keywords_ja": null,
      "createdById": 9,
      "updatedById": 9,
      "article_sub_tags": {
        "createdAt": "2026-03-28T18:24:57.914Z",
        "updatedAt": "2026-03-28T18:24:57.914Z",
        "articles_id": 957,
        "tags_id": 115
      }
    }
  ],
  "category": null,
  "cover": {
    "createdAt": "2026-03-28T18:24:48.927Z",
    "updatedAt": "2026-03-28T18:24:48.934Z",
    "id": 2306,
    "title": "develop (1)",
    "filename": "develop (1)-96561b.jpg",
    "extname": ".jpg",
    "size": 80755,
    "mimetype": "image/jpeg",
    "meta": {},
    "path": "",
    "url": "https://static-docs.nocobase.com/develop%20(1)-96561b.jpg",
    "preview": "https://static-docs.nocobase.com/develop%20(1)-96561b.jpg",
    "storageId": 2,
    "createdById": 22,
    "updatedById": 22
  },
  "hideOnListPage": false,
  "hideOnBlog": true,
  "author": "nocobase [bot]",
  "ai_generated": false,
  "ai_generated_cn": null,
  "ai_generated_ja": true,
  "updatedAt": "2026-03-28T18:24:57.898Z"
}