{
  "id": 656,
  "title": "10 Open-Source Tools to Build Data Apps",
  "title_cn": "10 个开源工具，快速构建数据应用",
  "title_ja": "10 個のオープンソースツールでデータアプリを構築する",
  "description": null,
  "description_cn": null,
  "description_ja": null,
  "slug": "open-source-data-apps",
  "publishedAt": "2025-08-21T00:59:57.841Z",
  "status": "drafted",
  "tags": [
    {
      "createdAt": "2024-06-17T09:17:27.652Z",
      "updatedAt": "2024-11-24T05:34:17.499Z",
      "id": 3,
      "title": "Open source",
      "title_cn": "开源",
      "sort": 3,
      "description": "",
      "description_cn": "",
      "displayOnPage": false,
      "slug": "",
      "displayOnBlog": false,
      "keywords": "",
      "keywords_cn": "",
      "title_ja": "オープンソース",
      "description_ja": "",
      "keywords_ja": "",
      "createdById": 1,
      "updatedById": 9,
      "articlesTags": {
        "createdAt": "2025-08-21T05:50:08.521Z",
        "updatedAt": "2025-08-21T05:50:08.521Z",
        "tagId": 3,
        "articleId": 656
      }
    },
    {
      "createdAt": "2024-07-09T12:38:10.829Z",
      "updatedAt": "2024-11-24T05:34:20.070Z",
      "id": 19,
      "title": "No-Code News",
      "title_cn": "无代码资讯",
      "sort": 19,
      "description": "Stay updated with the latest news in the No-Code universe.",
      "description_cn": "无代码领域的最新信息。",
      "displayOnPage": true,
      "slug": "nocode-news",
      "displayOnBlog": true,
      "keywords": "No-code news, No-code updates, No-code technology, No-code trends, Latest in no-code, No-code insights, No-code platforms",
      "keywords_cn": "无代码新闻, 无代码更新, 无代码技术, 无代码趋势, 最新无代码信息, 无代码洞察, 无代码平台",
      "title_ja": "ノーコードニュース",
      "description_ja": "ノーコードの世界の最新ニュースを常に把握しましょう。",
      "keywords_ja": "ノーコードニュース, ノーコード更新, ノーコード技術, ノーコードトレンド, 最新のノーコード情報, ノーコードの洞察, ノーコードプラットフォーム",
      "createdById": 1,
      "updatedById": 9,
      "articlesTags": {
        "createdAt": "2025-08-21T05:50:08.522Z",
        "updatedAt": "2025-08-21T05:50:08.522Z",
        "tagId": 19,
        "articleId": 656
      }
    },
    {
      "createdAt": "2024-07-30T07:17:05.893Z",
      "updatedAt": "2024-11-24T05:34:21.310Z",
      "id": 26,
      "title": "data control",
      "title_cn": "数据控制",
      "sort": 26,
      "description": null,
      "description_cn": null,
      "displayOnPage": null,
      "slug": null,
      "displayOnBlog": null,
      "keywords": null,
      "keywords_cn": null,
      "title_ja": "データ制御",
      "description_ja": "このセクションでは、データ制御の方法について説明します。",
      "keywords_ja": "データ, 制御, 管理",
      "createdById": 1,
      "updatedById": 9,
      "articlesTags": {
        "createdAt": "2025-08-21T05:50:08.521Z",
        "updatedAt": "2025-08-21T05:50:08.521Z",
        "tagId": 26,
        "articleId": 656
      }
    },
    {
      "createdAt": "2024-08-09T16:25:01.244Z",
      "updatedAt": "2024-11-24T05:34:24.380Z",
      "id": 43,
      "title": "Data Model",
      "title_cn": "数据模型",
      "sort": 43,
      "description": null,
      "description_cn": null,
      "displayOnPage": null,
      "slug": null,
      "displayOnBlog": null,
      "keywords": null,
      "keywords_cn": null,
      "title_ja": "データモデル",
      "description_ja": null,
      "keywords_ja": null,
      "createdById": 1,
      "updatedById": 9,
      "articlesTags": {
        "createdAt": "2025-08-21T05:50:08.521Z",
        "updatedAt": "2025-08-21T05:50:08.521Z",
        "tagId": 43,
        "articleId": 656
      }
    },
    {
      "createdAt": "2025-03-06T15:27:06.442Z",
      "updatedAt": "2025-03-06T15:27:06.442Z",
      "id": 144,
      "title": "data visualization",
      "title_cn": "数据可视化",
      "sort": 143,
      "description": null,
      "description_cn": null,
      "displayOnPage": null,
      "slug": null,
      "displayOnBlog": null,
      "keywords": null,
      "keywords_cn": null,
      "title_ja": "データ可視化",
      "description_ja": null,
      "keywords_ja": null,
      "createdById": 1,
      "updatedById": 1,
      "articlesTags": {
        "createdAt": "2025-08-21T05:50:08.521Z",
        "updatedAt": "2025-08-21T05:50:08.521Z",
        "tagId": 144,
        "articleId": 656
      }
    },
    {
      "createdAt": "2025-05-26T10:22:05.981Z",
      "updatedAt": "2025-05-26T10:22:05.981Z",
      "id": 184,
      "title": "Data Integration Platforms",
      "title_cn": "数据集成平台",
      "sort": 182,
      "description": null,
      "description_cn": null,
      "displayOnPage": null,
      "slug": null,
      "displayOnBlog": null,
      "keywords": null,
      "keywords_cn": null,
      "title_ja": "データ統合プラットフォーム",
      "description_ja": null,
      "keywords_ja": null,
      "createdById": 3,
      "updatedById": 3,
      "articlesTags": {
        "createdAt": "2025-08-21T05:50:08.521Z",
        "updatedAt": "2025-08-21T05:50:08.521Z",
        "tagId": 184,
        "articleId": 656
      }
    },
    {
      "createdAt": "2025-08-09T12:10:30.598Z",
      "updatedAt": "2025-08-09T12:10:30.598Z",
      "id": 217,
      "title": "Database Tool",
      "title_cn": "数据库工具",
      "sort": 215,
      "description": null,
      "description_cn": null,
      "displayOnPage": null,
      "slug": null,
      "displayOnBlog": null,
      "keywords": null,
      "keywords_cn": null,
      "title_ja": "データベースツール",
      "description_ja": null,
      "keywords_ja": null,
      "createdById": 3,
      "updatedById": 3,
      "articlesTags": {
        "createdAt": "2025-08-21T05:50:08.522Z",
        "updatedAt": "2025-08-21T05:50:08.522Z",
        "tagId": 217,
        "articleId": 656
      }
    },
    {
      "createdAt": "2025-08-21T05:49:52.185Z",
      "updatedAt": "2025-08-21T05:49:52.185Z",
      "id": 226,
      "title": "data app",
      "title_cn": null,
      "sort": 224,
      "description": null,
      "description_cn": null,
      "displayOnPage": null,
      "slug": null,
      "displayOnBlog": null,
      "keywords": null,
      "keywords_cn": null,
      "title_ja": null,
      "description_ja": null,
      "keywords_ja": null,
      "createdById": 3,
      "updatedById": 3,
      "articlesTags": {
        "createdAt": "2025-08-21T05:50:08.522Z",
        "updatedAt": "2025-08-21T05:50:08.522Z",
        "tagId": 226,
        "articleId": 656
      }
    }
  ],
  "sub_tags": [],
  "category": null,
  "cover": null,
  "hideOnListPage": false,
  "hideOnBlog": true,
  "author": "Deng lijia",
  "ai_generated": false,
  "ai_generated_cn": null,
  "ai_generated_ja": true,
  "updatedAt": "2025-08-21T05:54:39.214Z"
}